pytest_coveragemarkers/README.md
pytest_coveragemarkers/__init__.py
pytest_coveragemarkers/coveragemarkers.py
pytest_coveragemarkers/filter_specs/__init__.py
pytest_coveragemarkers/filter_specs/epics_filter.json
pytest_coveragemarkers/filter_specs/no_filter.json
pytest_coveragemarkers/heirarchical/__init__.py
pytest_coveragemarkers/heirarchical/check_yaml.py
pytest_coveragemarkers/heirarchical/h.py
pytest_coveragemarkers/heirarchical/markers.yml
pytest_coveragemarkers/marker_specs/__init__.py
pytest_coveragemarkers/marker_specs/coverage_markers.yml
pytest_coveragemarkers/marker_specs/epics.yml
pytest_coveragemarkers/marker_specs/features.yml
pytest_coveragemarkers/marker_specs/jira/bugs.yml
pytest_coveragemarkers/plugin.py
pytest_coveragemarkers/utils/__init__.py
pytest_coveragemarkers/utils/checks.py
pytest_coveragemarkers/utils/yml_processing.py
pytest_coveragemarkers-3.3.3.dist-info/LICENSE
pytest_coveragemarkers-3.3.3.dist-info/METADATA
pytest_coveragemarkers-3.3.3.dist-info/WHEEL
pytest_coveragemarkers-3.3.3.dist-info/entry_points.txt
pytest_coveragemarkers-3.3.3.dist-info/RECORD
