Metadata-Version: 2.3
Name: pytest-coveragemarkers
Version: 3.3.3
Summary: Using pytest markers to track functional coverage and filtering of tests
License: MIT
Keywords: test,pytest,markers,coverage
Author: Gleams API user
Author-email: Stephen.Swannell+ghapi@gmail.com
Requires-Python: >=3.8.1,<3.13.0
Classifier: License :: OSI Approved :: MIT License
Classifier: Programming Language :: Python :: 3
Classifier: Programming Language :: Python :: 3.9
Classifier: Programming Language :: Python :: 3.10
Classifier: Programming Language :: Python :: 3.11
Classifier: Programming Language :: Python :: 3.12
Requires-Dist: PyYAML (>=5.4.1)
Requires-Dist: loguru (>=0.6.0,<0.7.0)
Requires-Dist: pytest (>=7.1.2,<8.0.0)
Requires-Dist: pytest-jtr (>=1.4.0)
Requires-Dist: pytest-xdist (>=2.5.0,<3.0.0)
Requires-Dist: rich (>=13.3.0,<14.0.0)
Requires-Dist: rule-engine (>=4.5.0,<5.0.0)
Requires-Dist: urllib3 (>2.2.1)
